{
    "transactions": [{
        "block1": [{
                "price": 25,
                "from": "Darcy",
                "to": "Lydia"
            },
            {
                "price": 100,
                "from": "Ander",
                "to": "Sum"
            },
            {
                "price": 10,
                "from": "Kane",
                "to": "Ash"
            }
        ],
        "block2": [{
                "price": 30,
                "from": "Ander",
                "to": "Apone"
            },
            {
                "price": 20,
                "from": "Emily",
                "to": "Jackson"
            },
            {
                "price": 5,
                "from": "Ander",
                "to": "Jackson"
            }
        ],
        "block3": [{
                "price": 62,
                "from": "Denise",
                "to": "Sum"
            },
            {
                "price": 32,
                "from": "Madison",
                "to": "Grace"
            }
        ],
        "block4": [{
                "price": 98,
                "from": "Ander",
                "to": "Sum"
            },
            {
                "price": 63,
                "from": "Ander",
                "to": "Emily"
            },
            {
                "price": 20,
                "from": "Rick",
                "to": "Ilsa"
            },
            {
                "price": 123,
                "from": "Victor",
                "to": "Rick"
            }
        ],
        "block5": [{
                "price": 60,
                "from": "Captain",
                "to": "Sum"
            },
            {
                "price": 32,
                "from": "Ander",
                "to": "Victor"
            }
        ]
    }]
}